shanu/__init__.py
shanu/ai/__init__.py
shanu/ai/llm.py
shanu/ai/prompts.py
shanu/printer/__init__.py
shanu/web/__init__.py
shanu/web/download.py
shanu-0.0.4.dist-info/METADATA
shanu-0.0.4.dist-info/WHEEL
shanu-0.0.4.dist-info/top_level.txt
shanu-0.0.4.dist-info/RECORD
